ktplotspy/__init__.py
ktplotspy/plot/__init__.py
ktplotspy/plot/plot_cpdb.py
ktplotspy/plot/plot_cpdb_chord.py
ktplotspy/plot/plot_cpdb_heatmap.py
ktplotspy/utils/settings.py
ktplotspy/utils/support.py
ktplotspy-0.3.4.dist-info/licenses/LICENSE
ktplotspy-0.3.4.dist-info/METADATA
ktplotspy-0.3.4.dist-info/WHEEL
ktplotspy-0.3.4.dist-info/top_level.txt
ktplotspy-0.3.4.dist-info/RECORD
