Metadata-Version: 2.4
Name: ktplotspy
Version: 0.3.4
Summary: Python library for plotting Cellphonedb results. Ported from ktplots R package.
Author-email: Kelvin Tuong <26215587+zktuong@users.noreply.github.com>
License: MIT License
Project-URL: homepage, https://github.com/zktuong/ktplotspy
Project-URL: repository, https://github.com/zktuong/ktplotspy
Keywords: cellphonedb,cpdb,plot_cpdb,ktplots,ligand-receptor,interaction
Classifier: License :: OSI Approved :: MIT License
Classifier: Intended Audience :: Developers
Classifier: Intended Audience :: Science/Research
Classifier: Programming Language :: Python :: 3
Requires-Python: >=3.11
License-File: LICENSE
Requires-Dist: pandas>=1.5.0
Requires-Dist: numpy>=1.0.0
Requires-Dist: plotnine>=0.13.0
Requires-Dist: seaborn>=0.12
Requires-Dist: requests>=2.28.0
Requires-Dist: pycirclize>=1.7.2
Provides-Extra: test
Requires-Dist: anndata<0.11.5,>=0.7.6; extra == "test"
Requires-Dist: black; extra == "test"
Requires-Dist: pytest-cov; extra == "test"
Provides-Extra: docs
Requires-Dist: scanpy; extra == "docs"
Requires-Dist: ipykernel; extra == "docs"
Requires-Dist: sphinx>=7; extra == "docs"
Requires-Dist: nbsphinx>=0.7.0; extra == "docs"
Requires-Dist: sphinx-autodoc-typehints>=2.0.0; extra == "docs"
Requires-Dist: sphinx_rtd_theme>=2.0.0; extra == "docs"
Requires-Dist: readthedocs-sphinx-ext>=1.0.0; extra == "docs"
Requires-Dist: recommonmark>=0.6.0; extra == "docs"
Dynamic: license-file
